ananta/__init__.py
ananta/ananta.py
ananta/config.py
ananta/config.py.orig
ananta/output.py
ananta/ssh.py
ananta/tui/__init__.py
ananta/tui/ansi.py
ananta-1.4.0.dist-info/METADATA
ananta-1.4.0.dist-info/WHEEL
ananta-1.4.0.dist-info/entry_points.txt
ananta-1.4.0.dist-info/licenses/LICENSE
ananta-1.4.0.dist-info/RECORD
