Metadata-Version: 2.4
Name: ananta
Version: 1.4.0
Summary: A command-line tool to execute commands on multiple remote hosts
License: MIT
License-File: LICENSE
Author: Chaiwat Suttipongsakul
Author-email: cwt@bashell.com
Requires-Python: >=3.10
Classifier: License :: OSI Approved :: MIT License
Classifier: Programming Language :: Python :: 3
Classifier: Programming Language :: Python :: 3.10
Classifier: Programming Language :: Python :: 3.11
Classifier: Programming Language :: Python :: 3.12
Classifier: Programming Language :: Python :: 3.13
Classifier: Programming Language :: Python :: 3.14
Provides-Extra: speed
Requires-Dist: asyncssh (>=2.20.0,<3.0.0)
Requires-Dist: tomli (>=1.0.0,<3.0.0) ; python_version < "3.11"
Requires-Dist: urwid (>=2.1.2)
Requires-Dist: uvloop (>=0.21.0,<0.23.0) ; (sys_platform != "win32") and (extra == "speed")
Requires-Dist: winloop (>=0.1.8,<0.4.0) ; (sys_platform == "win32") and (extra == "speed")
Project-URL: Homepage, https://github.com/cwt/ananta
Project-URL: Repository, https://github.com/cwt/ananta
Project-URL: Sourcehut Mirror, https://sr.ht/~cwt/ananta/
